{
    "example_source": [
        "▁我还",
        "澄清",
        "了",
        "在该",
        "会议上",
        "提出的",
        "若干",
        "事项",
        "。"
    ],
    "example_target": [
        "<s>",
        "▁i",
        "▁was",
        "▁able",
        "▁to",
        "▁provide",
        "▁clarification",
        "▁on",
        "▁some",
        "▁of",
        "▁the",
        "▁matters",
        "▁which",
        "▁were",
        "▁raised",
        "▁at",
        "▁that",
        "▁meeting",
        ".",
        "</s>"
    ],
    "hypotheses": [
        {
            "hypothesis": [
                "▁i",
                "▁also",
                "▁agree",
                "ed",
                "▁to",
                "▁the",
                "▁meeting",
                "▁of",
                "▁the",
                "▁meeting",
                "▁of",
                "▁the",
                "▁meeting",
                "▁of",
                "▁the",
                "▁meeting",
                "."
            ],
            "score": -24.162473678588867
        },
        {
            "hypothesis": [
                "▁i",
                "▁would",
                "▁like",
                "▁to",
                "▁respond",
                "▁to",
                "▁the",
                "▁meeting",
                "▁in",
                "▁the",
                "▁meeting",
                "▁of",
                "▁the",
                "▁meeting",
                "▁of",
                "▁the",
                "▁meeting",
                "."
            ],
            "score": -24.940629959106445
        },
        {
            "hypothesis": [
                "▁i",
                "▁also",
                "▁agree",
                "ed",
                "▁to",
                "▁the",
                "▁meeting",
                "▁of",
                "▁the",
                "▁meeting",
                "▁of",
                "▁the",
                "▁meeting",
                "▁of",
                "▁the",
                "▁meeting",
                "▁of",
                "▁the",
                "▁meeting",
                "."
            ],
            "score": -26.55733299255371
        },
        {
            "hypothesis": [
                "▁i",
                "▁would",
                "▁like",
                "▁to",
                "▁respond",
                "▁to",
                "▁the",
                "▁meeting",
                "▁in",
                "▁the",
                "▁meeting",
                "▁of",
                "▁the",
                "▁meeting",
                "▁of",
                "▁the",
                "▁meeting",
                "▁of",
                "▁the",
                "▁meeting",
                "."
            ],
            "score": -27.19017219543457
        },
        {
            "hypothesis": [
                "▁i",
                "▁would",
                "▁like",
                "▁to",
                "▁respond",
                "▁to",
                "▁the",
                "▁meeting",
                "▁in",
                "▁the",
                "▁meeting",
                "▁of",
                "▁the",
                "▁meeting",
                "▁on",
                "▁the",
                "▁meeting",
                "▁of",
                "▁the",
                "▁meeting",
                "."
            ],
            "score": -27.41009521484375
        },
        {
            "hypothesis": [
                "▁i",
                "▁would",
                "▁like",
                "▁to",
                "▁respond",
                "▁to",
                "▁the",
                "▁meeting",
                "▁in",
                "▁the",
                "▁meeting",
                "▁of",
                "▁the",
                "▁meeting",
                "▁in",
                "▁the",
                "▁meeting",
                "▁of",
                "▁the",
                "▁meeting",
                "."
            ],
            "score": -27.573867797851562
        },
        {
            "hypothesis": [
                "▁i",
                "▁would",
                "▁like",
                "▁to",
                "▁respond",
                "▁to",
                "▁the",
                "▁meeting",
                "▁in",
                "▁the",
                "▁meeting",
                "▁of",
                "▁the",
                "▁conference",
                "▁on",
                "▁the",
                "▁meeting",
                "▁of",
                "▁the",
                "▁meeting",
                "."
            ],
            "score": -28.036983489990234
        },
        {
            "hypothesis": [
                "▁i",
                "▁would",
                "▁like",
                "▁to",
                "▁respond",
                "▁to",
                "▁the",
                "▁meeting",
                "▁of",
                "▁the",
                "▁meeting",
                "▁of",
                "▁the",
                "▁meeting",
                "▁of",
                "▁the",
                "▁meeting",
                "▁of",
                "▁the",
                "▁meeting",
                "."
            ],
            "score": -28.049602508544922
        },
        {
            "hypothesis": [
                "▁i",
                "▁would",
                "▁like",
                "▁to",
                "▁respond",
                "▁to",
                "▁the",
                "▁meeting",
                "▁in",
                "▁the",
                "▁meeting",
                "▁of",
                "▁the",
                "▁meeting",
                "▁of",
                "▁the",
                "▁meeting",
                "▁of",
                "▁the",
                "▁meeting",
                "▁of",
                "▁the",
                "▁meeting",
                "."
            ],
            "score": -30.137880325317383
        },
        {
            "hypothesis": [
                "▁i",
                "▁would",
                "▁like",
                "▁to",
                "▁respond",
                "▁to",
                "▁the",
                "▁meeting",
                "▁in",
                "▁the",
                "▁meeting",
                "▁of",
                "▁the",
                "▁meeting",
                "▁on",
                "▁the",
                "▁meeting",
                "▁of",
                "▁the",
                "▁meeting",
                "▁of",
                "▁the",
                "▁meeting",
                "."
            ],
            "score": -30.38014793395996
        }
    ],
    "diagnostic_info": "eyJ0IjogIjIwMjQtMDktMTZUMDk6MzU6MzUuNjkzNzQyIiwgImgiOiAiMTlhZDIwZjVmMDk3IiwgInUiOiAiemhvbmd5dWFuX3BlbmcifQ=="
}