{
    "example_source": [
        "▁我还",
        "澄清",
        "了",
        "在该",
        "会议上",
        "提出的",
        "若干",
        "事项",
        "。"
    ],
    "example_target": [
        "<s>",
        "▁i",
        "▁was",
        "▁able",
        "▁to",
        "▁provide",
        "▁clarification",
        "▁on",
        "▁some",
        "▁of",
        "▁the",
        "▁matters",
        "▁which",
        "▁were",
        "▁raised",
        "▁at",
        "▁that",
        "▁meeting",
        ".",
        "</s>"
    ],
    "hypotheses": [
        {
            "hypothesis": [
                "▁i",
                "▁have",
                "▁also",
                "▁clarified",
                "▁a",
                "▁number",
                "▁of",
                "▁matters",
                "▁raised",
                "▁by",
                "▁the",
                "▁conference",
                "."
            ],
            "score": -13.393502235412598
        },
        {
            "hypothesis": [
                "▁i",
                "▁have",
                "▁also",
                "▁clarified",
                "▁a",
                "▁number",
                "▁of",
                "▁matters",
                "▁raised",
                "▁in",
                "▁the",
                "▁conference",
                "."
            ],
            "score": -13.675871849060059
        },
        {
            "hypothesis": [
                "▁i",
                "▁have",
                "▁also",
                "▁clarified",
                "▁a",
                "▁number",
                "▁of",
                "▁matters",
                "▁raised",
                "▁by",
                "▁the",
                "▁meeting",
                "."
            ],
            "score": -13.760144233703613
        },
        {
            "hypothesis": [
                "▁i",
                "▁have",
                "▁also",
                "▁clarified",
                "▁a",
                "▁number",
                "▁of",
                "▁matters",
                "▁raised",
                "▁in",
                "▁the",
                "▁meeting",
                "."
            ],
            "score": -13.929884910583496
        },
        {
            "hypothesis": [
                "▁a",
                "▁number",
                "▁of",
                "▁matters",
                "▁raised",
                "▁by",
                "▁the",
                "▁conference",
                "▁had",
                "▁been",
                "▁addressed",
                "."
            ],
            "score": -13.979239463806152
        },
        {
            "hypothesis": [
                "▁i",
                "▁have",
                "▁also",
                "▁clarified",
                "▁a",
                "▁number",
                "▁of",
                "▁issues",
                "▁raised",
                "▁by",
                "▁the",
                "▁conference",
                "."
            ],
            "score": -14.664887428283691
        },
        {
            "hypothesis": [
                "▁i",
                "▁have",
                "▁also",
                "▁clarified",
                "▁a",
                "▁number",
                "▁of",
                "▁issues",
                "▁raised",
                "▁by",
                "▁the",
                "▁meeting",
                "."
            ],
            "score": -14.998159408569336
        },
        {
            "hypothesis": [
                "▁i",
                "▁have",
                "▁also",
                "▁clarified",
                "▁a",
                "▁number",
                "▁of",
                "▁matters",
                "▁raised",
                "▁in",
                "▁the",
                "▁meeting",
                "▁of",
                "▁the",
                "▁conference",
                "."
            ],
            "score": -15.878863334655762
        },
        {
            "hypothesis": [
                "▁i",
                "▁have",
                "▁also",
                "▁clarified",
                "▁a",
                "▁number",
                "▁of",
                "▁matters",
                "▁raised",
                "▁by",
                "▁a",
                "▁number",
                "▁of",
                "▁matters",
                "▁raised",
                "▁by",
                "▁the",
                "▁conference",
                "."
            ],
            "score": -18.38093376159668
        },
        {
            "hypothesis": [
                "▁i",
                "▁have",
                "▁also",
                "▁clarified",
                "▁a",
                "▁number",
                "▁of",
                "▁matters",
                "▁raised",
                "▁by",
                "▁a",
                "▁number",
                "▁of",
                "▁matters",
                "▁of",
                "▁the",
                "▁conference",
                "."
            ],
            "score": -18.582246780395508
        }
    ],
    "diagnostic_info": "eyJ0IjogIjIwMjQtMDktMTZUMDk6MTE6MTguMjc2NTg1IiwgImgiOiAiMTlhZDIwZjVmMDk3IiwgInUiOiAiemhvbmd5dWFuX3BlbmcifQ=="
}